[
  {
    "img_path": "data/DRIVE/test/images/01_test.tif",
    "mean_uncertainty": 0.01019126083701849
  },
  {
    "img_path": "data/DRIVE/test/images/02_test.tif",
    "mean_uncertainty": 0.008295126259326935
  },
  {
    "img_path": "data/DRIVE/test/images/03_test.tif",
    "mean_uncertainty": 0.015705740079283714
  },
  {
    "img_path": "data/DRIVE/test/images/04_test.tif",
    "mean_uncertainty": 0.02372540347278118
  },
  {
    "img_path": "data/DRIVE/test/images/05_test.tif",
    "mean_uncertainty": 0.007091388572007418
  },
  {
    "img_path": "data/DRIVE/test/images/06_test.tif",
    "mean_uncertainty": 0.007739410735666752
  },
  {
    "img_path": "data/DRIVE/test/images/07_test.tif",
    "mean_uncertainty": 0.012836959213018417
  },
  {
    "img_path": "data/DRIVE/test/images/08_test.tif",
    "mean_uncertainty": 0.008992096409201622
  },
  {
    "img_path": "data/DRIVE/test/images/09_test.tif",
    "mean_uncertainty": 0.012249059975147247
  },
  {
    "img_path": "data/DRIVE/test/images/10_test.tif",
    "mean_uncertainty": 0.007903214544057846
  },
  {
    "img_path": "data/DRIVE/test/images/11_test.tif",
    "mean_uncertainty": 0.008999841287732124
  },
  {
    "img_path": "data/DRIVE/test/images/12_test.tif",
    "mean_uncertainty": 0.006711847614496946
  },
  {
    "img_path": "data/DRIVE/test/images/13_test.tif",
    "mean_uncertainty": 0.014140276238322258
  },
  {
    "img_path": "data/DRIVE/test/images/14_test.tif",
    "mean_uncertainty": 0.012735379859805107
  },
  {
    "img_path": "data/DRIVE/test/images/15_test.tif",
    "mean_uncertainty": 0.010834170505404472
  },
  {
    "img_path": "data/DRIVE/test/images/16_test.tif",
    "mean_uncertainty": 0.006693439558148384
  },
  {
    "img_path": "data/DRIVE/test/images/17_test.tif",
    "mean_uncertainty": 0.012165368534624577
  },
  {
    "img_path": "data/DRIVE/test/images/18_test.tif",
    "mean_uncertainty": 0.009324025362730026
  },
  {
    "img_path": "data/DRIVE/test/images/19_test.tif",
    "mean_uncertainty": 0.014072811231017113
  },
  {
    "img_path": "data/DRIVE/test/images/20_test.tif",
    "mean_uncertainty": 0.007955988869071007
  }
]